{
    "prepare_queue": {
        "installed": [],
        "uninstalled": []
    },
    "config_munge": {
        "files": {
            "res/xml/config.xml": {
                "parents": {
                    "/*": [
                        {
                            "xml": "<feature name=\"NativePageTransitions\"><param name=\"android-package\" value=\"com.telerik.plugins.nativepagetransitions.NativePageTransitions\" /><param name=\"onload\" value=\"true\" /></feature>",
                            "count": 1
                        }
                    ]
                }
            }
        }
    },
    "installed_plugins": {
        "br.com.dtmtec.plugins.carrier": {
            "PACKAGE_NAME": "com.ionicframework.buyandsellfront"
        },
        "com.cordova.plugins.sms": {
            "PACKAGE_NAME": "com.ionicframework.buyandsellfront"
        },
        "com.ionic.keyboard": {
            "PACKAGE_NAME": "com.ionicframework.buyandsellfront"
        },
        "com.verso.cordova.clipboard": {
            "PACKAGE_NAME": "com.ionicframework.buyandsellfront"
        },
        "cordova-plugin-camera": {
            "PACKAGE_NAME": "com.ionicframework.buyandsellfront"
        },
        "cordova-plugin-console": {
            "PACKAGE_NAME": "com.ionicframework.buyandsellfront"
        },
        "cordova-plugin-device": {
            "PACKAGE_NAME": "com.ionicframework.buyandsellfront"
        },
        "cordova-plugin-dialogs": {
            "PACKAGE_NAME": "com.ionicframework.buyandsellfront"
        },
        "cordova-plugin-file": {
            "PACKAGE_NAME": "com.ionicframework.buyandsellfront"
        },
        "cordova-plugin-inappbrowser": {
            "PACKAGE_NAME": "com.ionicframework.buyandsellfront"
        },
        "cordova-plugin-network-information": {
            "PACKAGE_NAME": "com.ionicframework.buyandsellfront"
        },
        "cordova-plugin-splashscreen": {
            "PACKAGE_NAME": "com.ionicframework.buyandsellfront"
        },
        "cordova-plugin-statusbar": {
            "PACKAGE_NAME": "com.ionicframework.buyandsellfront"
        },
        "cordova-plugin-whitelist": {
            "PACKAGE_NAME": "com.ionicframework.buyandsellfront"
        },
        "cordova-plugin-x-socialsharing": {
            "PACKAGE_NAME": "com.ionicframework.buyandsellfront"
        },
        "ionic-plugin-keyboard": {
            "PACKAGE_NAME": "com.ionicframework.buyandsellfront"
        },
        "cordova-plugin-file-transfer": {
            "PACKAGE_NAME": "com.pisixlabs.occazstreet"
        },
        "com.telerik.plugins.nativepagetransitions": {
            "PACKAGE_NAME": "com.pisixlabs.occazstreet"
        },
        "com.telerik.plugins.wkwebview": {
            "WKWEBVIEW_SERVER_PORT": "12344",
            "PACKAGE_NAME": "com.pisixlabs.occazstreet"
        }
    },
    "dependent_plugins": {}
}